{
    "projectName": "SimplePlatformer",
    "scene": {
        "topGameObjects": [
            {
                "id": "Rigidbody",
                "name": "Player",
                "uid": 18446744072489549447,
                "position": {
                    "x": 0.0,
                    "y": 0.0
                },
                "rotation": 0.0,
                "scale": {
                    "x": 1.0,
                    "y": 1.0
                },
                "lastOffset": {
                    "x": 0.0,
                    "y": 0.0
                },
                "data": {
                    "integers": {
                        "content": [
                            {
                                "key": "bodyType",
                                "value": 2
                            }
                        ]
                    },
                    "ulongs": {
                        "content": []
                    },
                    "floats": {
                        "content": [
                            {
                                "key": "mass",
                                "value": 1.0
                            },
                            {
                                "key": "linearDamping",
                                "value": 0.0
                            },
                            {
                                "key": "angularDamping",
                                "value": 0.05000000074505806
                            },
                            {
                                "key": "gravityScale",
                                "value": 1.0
                            }
                        ]
                    },
                    "strings": {
                        "content": []
                    },
                    "bools": {
                        "content": [
                            {
                                "key": "useAutoMass",
                                "value": false
                            }
                        ]
                    }
                },
                "codeBlocks": [],
                "children": [
                    {
                        "id": "Sprite",
                        "name": "Sprite",
                        "uid": 18446744071900085978,
                        "position": {
                            "x": 0.0,
                            "y": 0.0
                        },
                        "rotation": 0.0,
                        "scale": {
                            "x": 1.0,
                            "y": 1.0
                        },
                        "lastOffset": {
                            "x": 0.0,
                            "y": 0.0
                        },
                        "data": {
                            "integers": {
                                "content": [
                                    {
                                        "key": "orderInLayer",
                                        "value": 0
                                    }
                                ]
                            },
                            "ulongs": {
                                "content": [
                                    {
                                        "key": "image",
                                        "value": 0
                                    }
                                ]
                            },
                            "floats": {
                                "content": []
                            },
                            "strings": {
                                "content": []
                            },
                            "bools": {
                                "content": []
                            }
                        },
                        "codeBlocks": [],
                        "children": []
                    },
                    {
                        "id": "BoxCollider",
                        "name": "BoxCollider",
                        "uid": 18446744072889247475,
                        "position": {
                            "x": 0.0,
                            "y": 0.0
                        },
                        "rotation": 0.0,
                        "scale": {
                            "x": 1.0,
                            "y": 1.0
                        },
                        "lastOffset": {
                            "x": 0.0,
                            "y": 0.0
                        },
                        "data": {
                            "integers": {
                                "content": []
                            },
                            "ulongs": {
                                "content": []
                            },
                            "floats": {
                                "content": []
                            },
                            "strings": {
                                "content": []
                            },
                            "bools": {
                                "content": [
                                    {
                                        "key": "enabled",
                                        "value": true
                                    },
                                    {
                                        "key": "isTrigger",
                                        "value": false
                                    }
                                ]
                            }
                        },
                        "codeBlocks": [],
                        "children": []
                    }
                ]
            },
            {
                "id": "BoxCollider",
                "name": "Ground",
                "uid": 1998521682,
                "position": {
                    "x": 0.0,
                    "y": -10.0
                },
                "rotation": 0.0,
                "scale": {
                    "x": 200.0,
                    "y": 5.0
                },
                "lastOffset": {
                    "x": 0.0,
                    "y": 0.0
                },
                "data": {
                    "integers": {
                        "content": []
                    },
                    "ulongs": {
                        "content": []
                    },
                    "floats": {
                        "content": []
                    },
                    "strings": {
                        "content": []
                    },
                    "bools": {
                        "content": [
                            {
                                "key": "enabled",
                                "value": true
                            },
                            {
                                "key": "isTrigger",
                                "value": false
                            }
                        ]
                    }
                },
                "codeBlocks": [],
                "children": [
                    {
                        "id": "Sprite",
                        "name": "Sprite",
                        "uid": 1774773952,
                        "position": {
                            "x": 0.0,
                            "y": 0.0
                        },
                        "rotation": 0.0,
                        "scale": {
                            "x": 1.0,
                            "y": 1.0
                        },
                        "lastOffset": {
                            "x": 0.0,
                            "y": 0.0
                        },
                        "data": {
                            "integers": {
                                "content": [
                                    {
                                        "key": "orderInLayer",
                                        "value": 0
                                    }
                                ]
                            },
                            "ulongs": {
                                "content": [
                                    {
                                        "key": "image",
                                        "value": 0
                                    }
                                ]
                            },
                            "floats": {
                                "content": []
                            },
                            "strings": {
                                "content": []
                            },
                            "bools": {
                                "content": []
                            }
                        },
                        "codeBlocks": [],
                        "children": []
                    }
                ]
            }
        ]
    },
    "assets": []
}